fastspell_dictionaries/__init__.py
fastspell_dictionaries/af_ZA.aff
fastspell_dictionaries/af_ZA.dic
fastspell_dictionaries/af_ZA.license
fastspell_dictionaries/am_ET.aff
fastspell_dictionaries/am_ET.dic
fastspell_dictionaries/am_ET.license
fastspell_dictionaries/an_ES.aff
fastspell_dictionaries/an_ES.dic
fastspell_dictionaries/an_ES.license
fastspell_dictionaries/ar.aff
fastspell_dictionaries/ar.dic
fastspell_dictionaries/ar.license
fastspell_dictionaries/ast.license
fastspell_dictionaries/ast_ES.aff
fastspell_dictionaries/ast_ES.dic
fastspell_dictionaries/awa.aff
fastspell_dictionaries/awa.dic
fastspell_dictionaries/awa.license
fastspell_dictionaries/az_AZ.aff
fastspell_dictionaries/az_AZ.dic
fastspell_dictionaries/az_AZ.license
fastspell_dictionaries/be_BY.aff
fastspell_dictionaries/be_BY.dic
fastspell_dictionaries/be_BY.license
fastspell_dictionaries/bg_BG.aff
fastspell_dictionaries/bg_BG.dic
fastspell_dictionaries/bg_BG.license
fastspell_dictionaries/bho.aff
fastspell_dictionaries/bho.dic
fastspell_dictionaries/bho.license
fastspell_dictionaries/bn_BD.aff
fastspell_dictionaries/bn_BD.dic
fastspell_dictionaries/bn_BD.license
fastspell_dictionaries/bs_BA.aff
fastspell_dictionaries/bs_BA.dic
fastspell_dictionaries/bs_BA.license
fastspell_dictionaries/ca_ES.aff
fastspell_dictionaries/ca_ES.dic
fastspell_dictionaries/ca_ES.license
fastspell_dictionaries/cs_CZ.aff
fastspell_dictionaries/cs_CZ.dic
fastspell_dictionaries/cs_CZ.license
fastspell_dictionaries/cy.aff
fastspell_dictionaries/cy.dic
fastspell_dictionaries/cy.license
fastspell_dictionaries/cy_GB.aff
fastspell_dictionaries/cy_GB.dic
fastspell_dictionaries/cy_GB.license
fastspell_dictionaries/da_DK.aff
fastspell_dictionaries/da_DK.dic
fastspell_dictionaries/da_DK.license
fastspell_dictionaries/de_DE.aff
fastspell_dictionaries/de_DE.dic
fastspell_dictionaries/de_DE.license
fastspell_dictionaries/en_GB.aff
fastspell_dictionaries/en_GB.dic
fastspell_dictionaries/en_GB.license
fastspell_dictionaries/es_ES.aff
fastspell_dictionaries-3.3.dist-info/LICENSE
fastspell_dictionaries-3.3.dist-info/METADATA
fastspell_dictionaries-3.3.dist-info/WHEEL
fastspell_dictionaries-3.3.dist-info/top_level.txt
fastspell_dictionaries-3.3.dist-info/RECORD
