Metadata-Version: 2.1
Name: fastspell-dictionaries
Version: 3.3
Summary: Hunspell dictionaries for FastSpell
Author-email: Prompsit Language Engineering <info@prompsit.com>
Maintainer-email: Marta Bañon <mbanon@prompsit.com>, Jaume Zaragoza <jzaragoza@prompsit.com>
License: See *.license file for each dictionary.
Project-URL: Homepage, https://github.com/mbanon/fastspell
Project-URL: FastSpell on GitHub, https://github.com/mbanon/fastspell
Project-URL: Prompsit Language Engineering, http://prompsit.com
Project-URL: Paracrawl, https://paracrawl.eu
Project-URL: MaCoCu, https://macocu.eu
Project-URL: HPLT, https://hplt-project.org
Requires-Python: >=3.8
License-File: LICENSE
